zabel/core/__init__.py
zabel/core/storage.py
zabel/core/accounts/__init__.py
zabel/core/manifests/bootstrap.yaml
zabel/core/projects/__init__.py
zabel/core/projects/domainprovidermpd.py
zabel/core/projects/mpdmanager.py
zabel/core/services/__init__.py
zabel-0.13.0.dist-info/LICENSE.txt
zabel-0.13.0.dist-info/METADATA
zabel-0.13.0.dist-info/WHEEL
zabel-0.13.0.dist-info/top_level.txt
zabel-0.13.0.dist-info/RECORD
